script_queue_manager/__init__.py
script_queue_manager/executor.py
script_queue_manager/prescripts.txt
script_queue_manager/pusher.py
script_queue_manager-0.0.4.dist-info/LICENSE
script_queue_manager-0.0.4.dist-info/METADATA
script_queue_manager-0.0.4.dist-info/WHEEL
script_queue_manager-0.0.4.dist-info/entry_points.txt
script_queue_manager-0.0.4.dist-info/top_level.txt
script_queue_manager-0.0.4.dist-info/RECORD
