Metadata-Version: 2.1
Name: script-queue-manager
Version: 0.0.4
Summary: A CLI tool to manage script queue
Home-page: https://github.com/mayank8318/script-queue-manager
Author: Mayank Vaidya
Author-email: mayank8318@gmail.com
License: MIT
Keywords: script_queue_manager manage-tasks queue tasks python package mayank8318
Platform: UNKNOWN
Classifier: Programming Language :: Python :: 3
Classifier: License :: OSI Approved :: MIT License
Classifier: Operating System :: OS Independent
Requires-Dist: persist-queue
